iflow_mcp_finq4cn_mcp_server-0.1.0.dist-info/licenses/LICENSE
mcp_server/fs_server.py
mcp_server/utils/__init__.py
mcp_server/utils/backtesting.py
mcp_server/utils/modules.py
mcp_server/utils/news_report.py
mcp_server/utils/quant_analysis.py
mcp_server/utils/stocks_common_metrics.py
mcp_server/utils/stocks_risk_alert.py
mcp_server/utils/tools.py
iflow_mcp_finq4cn_mcp_server-0.1.0.dist-info/METADATA
iflow_mcp_finq4cn_mcp_server-0.1.0.dist-info/WHEEL
iflow_mcp_finq4cn_mcp_server-0.1.0.dist-info/entry_points.txt
iflow_mcp_finq4cn_mcp_server-0.1.0.dist-info/top_level.txt
iflow_mcp_finq4cn_mcp_server-0.1.0.dist-info/RECORD
