Metadata-Version: 2.4
Name: iflow-mcp_FinQ4Cn-mcp-server
Version: 0.1.0
Summary: A dedicated MCP server for quantitative analysis of China's A-share market
Requires-Python: >=3.10
License-File: LICENSE
Requires-Dist: mcp==1.6.0
Requires-Dist: pydantic==2.11.1
Requires-Dist: akshare==1.16.73
Requires-Dist: pandas==2.2.3
Requires-Dist: backtrader==1.9.78.123
Requires-Dist: lib-pybroker==1.2.5
Requires-Dist: matplotlib
Dynamic: license-file
